{
  "author": "Hyeseong Kim",
  "auto_category": "high_priority",
  "date": "2024-11-20 09:54:05 +0900",
  "discovered_at": "2026-03-26T14:34:44.398727",
  "files_changed": [
    "CHANGELOG.md",
    "compiler/ext/js_reserved_map.ml",
    "tests/tests/src/global_mangles.mjs",
    "tests/tests/src/global_mangles.res",
    "tests/tests/src/ident_mangles.mjs",
    "tests/tests/src/ident_mangles.res",
    "tests/tests/src/key_word_property_plus_test.mjs",
    "tests/tests/src/key_word_property_plus_test.res"
  ],
  "hash": "92477bd84",
  "melange_branch": "",
  "notes": [],
  "plan": "",
  "pr_url": "",
  "reason": "",
  "status": "discovered",
  "subject": "Fix `arguments` and `eval` mangling (#7163)",
  "updated_at": "2026-03-26T14:34:44.398768"
}